{"version":1,"resource":"file:///Users/pm/Project/tech_by_tech/packages/common/lib/src/widgets/app_bar.dart","entries":[{"id":"UPnc.dart","timestamp":1658328473999},{"id":"UvXS.dart","timestamp":1658328660162},{"id":"bh2X.dart","timestamp":1658328993467},{"id":"21s6.dart","timestamp":1658329011094},{"id":"28ZM.dart","timestamp":1658329082538},{"id":"6DVo.dart","timestamp":1658329098910},{"id":"BGzz.dart","timestamp":1658329130241},{"id":"qfdG.dart","timestamp":1658329206967},{"id":"zY52.dart","timestamp":1658329233208},{"id":"vlwc.dart","timestamp":1658329249679},{"id":"3mJT.dart","timestamp":1658329272576},{"id":"x0AK.dart","timestamp":1658329514207},{"id":"BkX6.dart","timestamp":1658329530199},{"id":"9Cgq.dart","timestamp":1658329544567},{"id":"Fe8k.dart","timestamp":1658329564026},{"id":"LISJ.dart","timestamp":1658329606254},{"id":"D2pO.dart","timestamp":1658329735060},{"id":"Tcv8.dart","timestamp":1658330112523},{"id":"JPxk.dart","timestamp":1658330343299},{"id":"cyH0.dart","timestamp":1658330365930},{"id":"aBw5.dart","timestamp":1658330396307},{"id":"ko0u.dart","timestamp":1658330427057},{"id":"pj8v.dart","timestamp":1658330630636},{"id":"78xR.dart","timestamp":1658330679079},{"id":"92Xu.dart","timestamp":1658330696459},{"id":"2eir.dart","timestamp":1658330901347},{"id":"nOVQ.dart","timestamp":1658330954546},{"id":"Wjhm.dart","timestamp":1658330975603},{"id":"D5ox.dart","timestamp":1658330991056},{"id":"My3F.dart","timestamp":1658331049583},{"id":"DgTW.dart","timestamp":1658331478333},{"id":"7F9b.dart","timestamp":1658331499375},{"id":"Lvy8.dart","timestamp":1658331511613},{"id":"fzBj.dart","timestamp":1658331524019},{"id":"ubGX.dart","timestamp":1658331620555},{"id":"CPx8.dart","timestamp":1658331960695},{"id":"NkXf.dart","timestamp":1658331981781},{"id":"wuJp.dart","timestamp":1658331993577},{"id":"6kK9.dart","timestamp":1658332079600},{"id":"480S.dart","timestamp":1658332151919},{"id":"wIEE.dart","timestamp":1658332182696},{"id":"rpBb.dart","timestamp":1658332714061},{"id":"Q8kZ.dart","timestamp":1658332998193},{"id":"aVsw.dart","timestamp":1658333028167},{"id":"sET7.dart","timestamp":1658333143918},{"id":"z0aG.dart","timestamp":1658333401868},{"id":"pLNz.dart","timestamp":1658333415192},{"id":"fPxm.dart","timestamp":1658333472105},{"id":"6yiE.dart","timestamp":1658333482268},{"id":"t1Mt.dart","timestamp":1658333509682}]}