{"version":1,"resource":"file:///Users/pm/Project/tech_by_tech/tech_by_tech/packages/common/lib/src/widgets/chips/info_chip.dart","entries":[{"id":"YcA9.dart","source":"undoRedo.source","timestamp":1660580131577},{"id":"jezf.dart","timestamp":1660580147093},{"id":"K0s6.dart","source":"Import library 'package:flutter/material.dart'","timestamp":1660580154765},{"id":"Tkg3.dart","timestamp":1660580157434},{"id":"fEZB.dart","timestamp":1660580184725},{"id":"5teh.dart","source":"Renaming IconTextChip to InfoChip","timestamp":1660580199066},{"id":"NhRV.dart","timestamp":1660580240310},{"id":"GsRL.dart","source":"renamed.source","timestamp":1660580341460},{"id":"joBW.dart","timestamp":1660580620115},{"id":"QQ98.dart","source":"undoRedo.source","timestamp":1660580623681},{"id":"RSic.dart","timestamp":1660580630255},{"id":"Dtyb.dart","timestamp":1660580844970},{"id":"Nras.dart","timestamp":1660580866926},{"id":"guP4.dart","timestamp":1660581047503},{"id":"Uh6N.dart","timestamp":1660581091654},{"id":"ChEN.dart","timestamp":1660581257135}]}