{"version":1,"resource":"file:///Users/pm/Project/bonemeal/bonemeal/bonemeal/lib/src/asset/id.dart","entries":[{"id":"cRUu.dart","timestamp":1654001838829},{"id":"Gu65.dart","timestamp":1654002091471},{"id":"3ODt.dart","timestamp":1654002106223},{"id":"QmDf.dart","timestamp":1654002161596},{"id":"aJ6t.dart","source":"undoRedo.source","timestamp":1654002207308},{"id":"JTan.dart","timestamp":1654002213051},{"id":"9fpB.dart","timestamp":1654002296308},{"id":"NT0T.dart","timestamp":1654002331424},{"id":"XLoZ.dart","timestamp":1654002343010},{"id":"09Kd.dart","timestamp":1654002381349},{"id":"qhFk.dart","timestamp":1654002496151},{"id":"SN21.dart","timestamp":1654002513301},{"id":"fvFA.dart","timestamp":1654002536551},{"id":"y9Sz.dart","timestamp":1654002553469},{"id":"W346.dart","timestamp":1654002604766},{"id":"5R89.dart","timestamp":1654002624978},{"id":"KRvz.dart","timestamp":1654002662325},{"id":"NYVz.dart","timestamp":1654002677151},{"id":"AsR6.dart","source":"undoRedo.source","timestamp":1654002684327},{"id":"oStw.dart","timestamp":1654002697773},{"id":"jUQL.dart","source":"Renaming package to type","timestamp":1654002704592},{"id":"sXQY.dart","timestamp":1654002723885},{"id":"NQoZ.dart","timestamp":1654002735802},{"id":"mjYq.dart","timestamp":1654006237818},{"id":"Yofy.dart","timestamp":1654006260466},{"id":"qFio.dart","timestamp":1654070436581},{"id":"UHJz.dart","timestamp":1654070511810}]}