{"version":1,"resource":"file:///Users/pm/Project/zanalys/ipr_zanalys/lib/src/form/multi_line_form_field.dart","entries":[{"id":"jSSL.dart","timestamp":1659110506583},{"id":"UirV.dart","timestamp":1659110617616},{"id":"3R9I.dart","timestamp":1660231544155},{"id":"VWk3.dart","timestamp":1660231563895},{"id":"hoZD.dart","source":"undoRedo.source","timestamp":1660231590073},{"id":"xzsb.dart","timestamp":1660233769358},{"id":"G06W.dart","timestamp":1660233819686},{"id":"jiTs.dart","timestamp":1660233937940},{"id":"J4J3.dart","timestamp":1660233951800},{"id":"L98P.dart","timestamp":1660233995533},{"id":"bZxB.dart","timestamp":1660234005674},{"id":"9TLg.dart","timestamp":1660234032419},{"id":"loq8.dart","timestamp":1660234065313},{"id":"YcBU.dart","timestamp":1660234153556},{"id":"jMSs.dart","timestamp":1660234169930},{"id":"xvmh.dart","timestamp":1660234182775},{"id":"CsNP.dart","timestamp":1660234193195},{"id":"MAQu.dart","timestamp":1660234294246},{"id":"TGLH.dart","timestamp":1660234349383},{"id":"UMVZ.dart","timestamp":1660234364186},{"id":"iDV7.dart","timestamp":1660234386552},{"id":"TXE1.dart","timestamp":1660234585244},{"id":"Rwa0.dart","timestamp":1660234611518},{"id":"jmXv.dart","timestamp":1660234628645},{"id":"hdsa.dart","timestamp":1660234665765},{"id":"RWgt.dart","timestamp":1660235115649},{"id":"UBYU.dart","timestamp":1660235168704},{"id":"Q1I0.dart","source":"undoRedo.source","timestamp":1660235178307},{"id":"Sz8i.dart","timestamp":1660235237308},{"id":"eofg.dart","timestamp":1660235255758},{"id":"UOSV.dart","timestamp":1660235287207},{"id":"00AA.dart","timestamp":1660235318803},{"id":"C0Ci.dart","timestamp":1660235341333},{"id":"cloZ.dart","timestamp":1660235355496},{"id":"zdXy.dart","timestamp":1660235394346},{"id":"Kn7y.dart","timestamp":1660235415606},{"id":"lgN4.dart","timestamp":1660235447983},{"id":"sRyX.dart","timestamp":1660235652882},{"id":"1XHP.dart","timestamp":1660235691990},{"id":"GVEz.dart","timestamp":1660235702249},{"id":"xUqv.dart","timestamp":1660235726602},{"id":"mD4j.dart","timestamp":1660279867005},{"id":"29HM.dart","timestamp":1660279892680},{"id":"0gY0.dart","timestamp":1660279916336}]}