{"version":1,"resource":"file:///Users/pm/Project/bonemeal/src/generators/fetch_generators/lib/src/fetch_bloc/fetch_bloc.g.dart","entries":[{"id":"cqpk.dart","source":"Renaming MetaFetchSmbData to MetaFetchBlocData","timestamp":1654870934377},{"id":"h224.dart","source":"Renaming _Source to Source","timestamp":1654870991940},{"id":"QXzt.dart","source":"Renaming Source to _Source","timestamp":1654871182606},{"id":"RPY0.dart","source":"Renaming MetaFetchBlocData to FetchBlocOPtions","timestamp":1654872045280},{"id":"yT7e.dart","source":"Renaming FetchBlocOPtions to FetchBlocOptions","timestamp":1654872050515},{"id":"eHX8.dart","timestamp":1654872081779},{"id":"d8lu.dart","source":"Renaming FetchBlocSource to FetchBlocSourceOptions","timestamp":1654872116285},{"id":"ooJY.dart","timestamp":1654872139042}]}