{"version":1,"resource":"file:///Users/pm/Project/tech_by_tech/packages/common/lib/src/ui_kit/switches.dart","entries":[{"id":"laPS.dart","timestamp":1657693742777},{"id":"Q8Gg.dart","timestamp":1657693759822},{"id":"jYTr.dart","timestamp":1657693839346},{"id":"aguK.dart","timestamp":1657693938356},{"id":"Jy6O.dart","timestamp":1657693958429},{"id":"htYl.dart","timestamp":1657693979793},{"id":"bYwt.dart","timestamp":1657694083335},{"id":"uZWK.dart","timestamp":1657694109522},{"id":"rklx.dart","timestamp":1657694195414},{"id":"ElUd.dart","source":"Import library 'package:common/common.dart'","timestamp":1657694203361},{"id":"Tb6w.dart","timestamp":1657694868550},{"id":"dR4o.dart","timestamp":1657694887014},{"id":"MCkO.dart","timestamp":1657694905061},{"id":"C1qM.dart","timestamp":1657694917960},{"id":"socy.dart","timestamp":1657695023874},{"id":"aNBm.dart","timestamp":1657695040346},{"id":"CXsN.dart","timestamp":1657695051755},{"id":"rhnb.dart","timestamp":1657695165187},{"id":"ZBA4.dart","timestamp":1657695308714},{"id":"shQk.dart","timestamp":1657695334004},{"id":"e67f.dart","timestamp":1657695401166},{"id":"xGYl.dart","source":"Add curly braces","timestamp":1657695413002},{"id":"H0eo.dart","timestamp":1657695451130},{"id":"rN3R.dart","timestamp":1657695471507},{"id":"Uqrp.dart","timestamp":1657695542176},{"id":"OGBQ.dart","timestamp":1657695557043},{"id":"uqdY.dart","timestamp":1657695578111},{"id":"ojrb.dart","timestamp":1657695590474},{"id":"DyJT.dart","timestamp":1657695625415},{"id":"zrsS.dart","timestamp":1657695667976},{"id":"n30b.dart","timestamp":1657695740854},{"id":"wX1I.dart","source":"Remove this widget","timestamp":1657695746555}]}