{"version":1,"resource":"file:///Users/pm/Project/bonemeal/src/generators/fetch_generators/lib/src/fetch_bloc/fetch_bloc.dart","entries":[{"id":"y6jF.dart","timestamp":1655044393992},{"id":"9pWT.dart","timestamp":1655044413157},{"id":"ZJ6U.dart","timestamp":1655044454513},{"id":"M7Tf.dart","timestamp":1655044536817},{"id":"lIXI.dart","source":"undoRedo.source","timestamp":1655044541567},{"id":"2VBl.dart","timestamp":1655044561299},{"id":"6HsZ.dart","timestamp":1655044573221},{"id":"UYka.dart","source":"undoRedo.source","timestamp":1655044579259},{"id":"0sui.dart","timestamp":1655044584062},{"id":"szgS.dart","timestamp":1655044611243},{"id":"0CIM.dart","timestamp":1655044638765},{"id":"j041.dart","timestamp":1655044659138},{"id":"hDw0.dart","timestamp":1655044797210},{"id":"KthR.dart","timestamp":1655044936953},{"id":"amGO.dart","timestamp":1655044953201},{"id":"p9eK.dart","source":"undoRedo.source","timestamp":1655044982295},{"id":"xuq2.dart","timestamp":1655044988219},{"id":"VPN5.dart","timestamp":1655045107978},{"id":"5op9.dart","source":"undoRedo.source","timestamp":1655045111654},{"id":"6YOO.dart","timestamp":1655045137602},{"id":"m4AA.dart","timestamp":1655045147863},{"id":"BrHa.dart","timestamp":1655045172413},{"id":"u6P6.dart","timestamp":1655045184060},{"id":"Ep2x.dart","timestamp":1655045234822},{"id":"mjDy.dart","timestamp":1655045245874},{"id":"omp0.dart","source":"undoRedo.source","timestamp":1655045266798},{"id":"EbKj.dart","source":"undoRedo.source","timestamp":1655045279902},{"id":"d7JH.dart","timestamp":1655045294860},{"id":"VSOm.dart","timestamp":1655045313479},{"id":"qVZD.dart","timestamp":1655045566717},{"id":"H4SL.dart","timestamp":1655045999531},{"id":"KA6Y.dart","source":"Renaming blocarams to blocParams","timestamp":1655046027009},{"id":"Atzz.dart","timestamp":1655046181957},{"id":"LHjL.dart","timestamp":1655046214487},{"id":"OZ71.dart","timestamp":1655046228391},{"id":"J30z.dart","timestamp":1655046243206},{"id":"nHsY.dart","timestamp":1655046271144},{"id":"hMad.dart","timestamp":1655046411157},{"id":"xrlH.dart","timestamp":1655046489138},{"id":"iEkB.dart","timestamp":1655046567867},{"id":"abdn.dart","timestamp":1655046591527},{"id":"jRg4.dart","timestamp":1655046608900},{"id":"K05h.dart","timestamp":1655046666724},{"id":"Eh6i.dart","source":"undoRedo.source","timestamp":1655046676301},{"id":"4THJ.dart","timestamp":1655046695307},{"id":"mWH9.dart","timestamp":1655047008317},{"id":"Mspf.dart","timestamp":1655047044226},{"id":"XwLc.dart","timestamp":1655048367494},{"id":"YCKm.dart","source":"Workspace Edit","timestamp":1655048399047},{"id":"QirE.dart","timestamp":1655098879433}]}