{"version":1,"resource":"file:///Users/pm/Project/zanalys/zanalys-app-flutter/packages/zanalys_api/lib/src/record_api/models/new_record_body.dart","entries":[{"id":"2aLy.dart","source":"Import library 'package:models/models.dart'","timestamp":1657803843865},{"id":"V7ZI.dart","timestamp":1657803928509},{"id":"3ChG.dart","timestamp":1657803988057},{"id":"Sski.dart","timestamp":1657804066187},{"id":"rBMp.dart","timestamp":1657804345026},{"id":"wEkU.dart","timestamp":1657806784627},{"id":"6Lcu.dart","timestamp":1657806796881},{"id":"M1zS.dart","source":"Import library 'package:freezed_annotation/freezed_annotation.dart'","timestamp":1657806848285},{"id":"wLnU.dart","timestamp":1657806889822},{"id":"dOY7.dart","timestamp":1657806927401},{"id":"Gcv9.dart","timestamp":1657807659532},{"id":"zAbc.dart","timestamp":1657807693249},{"id":"dps1.dart","timestamp":1657807753696},{"id":"a58v.dart","source":"Import library 'package:freezed_annotation/freezed_annotation.dart'","timestamp":1657807772282},{"id":"ZqYX.dart","timestamp":1657825373883}]}