{"version":1,"resource":"file:///Users/pm/Project/ftool/pepper/bin/pepper.dart","entries":[{"id":"SGM3.dart","timestamp":1648928002170},{"id":"M7VX.dart","timestamp":1648928015611},{"id":"lyYG.dart","timestamp":1648928031317},{"id":"Q7Yp.dart","timestamp":1648928059433},{"id":"S5cg.dart","timestamp":1648929104898},{"id":"48s3.dart","timestamp":1648929590011},{"id":"1q5f.dart","timestamp":1648929617915},{"id":"1btI.dart","timestamp":1648929633334},{"id":"4ki7.dart","timestamp":1648929661282},{"id":"sN8C.dart","timestamp":1648929673760},{"id":"QKnF.dart","timestamp":1648929689529},{"id":"gcxz.dart","timestamp":1648929713988},{"id":"RrCg.dart","timestamp":1648929742276},{"id":"mnAi.dart","timestamp":1648929758361},{"id":"Z9rr.dart","timestamp":1648929951125},{"id":"tgKP.dart","timestamp":1648929977189},{"id":"5Fwk.dart","timestamp":1648929987327},{"id":"x5V5.dart","timestamp":1648930035058},{"id":"75NE.dart","timestamp":1648930067734},{"id":"QCoT.dart","timestamp":1648930138906},{"id":"ToLS.dart","timestamp":1648930370503},{"id":"VynT.dart","timestamp":1648930392297},{"id":"M1KM.dart","timestamp":1648930495532},{"id":"ybkF.dart","timestamp":1648930527938},{"id":"ujrd.dart","timestamp":1648930547470},{"id":"c9P1.dart","timestamp":1648930568111}]}