{"version":1,"resource":"file:///Users/pm/Project/tech_by_tech/tech_by_tech/packages/tbt_api/lib/src/utils/unwrap_response.dart","entries":[{"id":"8AxF.dart","timestamp":1659067135789},{"id":"lWNT.dart","timestamp":1659067152767},{"id":"EZg4.dart","timestamp":1659067179809},{"id":"T5ok.dart","timestamp":1659067327738},{"id":"kq3d.dart","source":"undoRedo.source","timestamp":1659067369335},{"id":"2egQ.dart","timestamp":1659067390631},{"id":"fbtI.dart","timestamp":1659067414942},{"id":"lYBs.dart","timestamp":1659067474079}]}