{"version":1,"resource":"file:///Users/pm/Project/zanalys/zanalys-app-flutter/packages/models/lib/src/records/record/provider_consultation.dart","entries":[{"id":"SQZq.dart","timestamp":1657969300637},{"id":"c9fN.dart","timestamp":1657969363782},{"id":"GakW.dart","timestamp":1657969391576},{"id":"GkCW.dart","timestamp":1657969476576},{"id":"L2yf.dart","timestamp":1657969519006},{"id":"JjW7.dart","timestamp":1657969703160},{"id":"QsCx.dart","timestamp":1657969770879},{"id":"SSLA.dart","timestamp":1657969802153},{"id":"cCgr.dart","timestamp":1657969822712},{"id":"hSqa.dart","timestamp":1657969844767},{"id":"3uou.dart","timestamp":1657969855441},{"id":"GIAj.dart","timestamp":1657969875531},{"id":"Dzdu.dart","timestamp":1657969915609},{"id":"5qiT.dart","timestamp":1657969931329},{"id":"daH5.dart","timestamp":1657970100217},{"id":"ZeW1.dart","timestamp":1657986460220},{"id":"FC76.dart","timestamp":1657992552304},{"id":"VLbz.dart","timestamp":1657992832285},{"id":"Y4TI.dart","timestamp":1657992860818},{"id":"Vn6z.dart","timestamp":1657992877197},{"id":"VPO4.dart","timestamp":1657992892605},{"id":"EFbr.dart","timestamp":1657992955844},{"id":"Fy3D.dart","timestamp":1657992997952},{"id":"9vsg.dart","timestamp":1657993015246},{"id":"z95d.dart","source":"moved.source","timestamp":1657994535996},{"id":"Nh2U.dart","source":"moved.source","timestamp":1657994537529},{"id":"eJya.dart","timestamp":1657994595423},{"id":"L1u8.dart","timestamp":1657994613725}]}