{"version":1,"resource":"file:///Users/pm/Project/zanalys-app-flutter/lib/auth/models/login_status.dart","entries":[{"id":"0fp1.dart","timestamp":1654525851884},{"id":"s63i.dart","timestamp":1654525869891},{"id":"tYAD.dart","source":"Renaming UserSignInStatus to LogInStatus","timestamp":1654525878606},{"id":"YA9e.dart","timestamp":1654528361433},{"id":"rXZJ.dart","timestamp":1654528380180},{"id":"nkRf.dart","source":"moved.source","timestamp":1654528689132},{"id":"yObH.dart","source":"renamed.source","timestamp":1654528828434},{"id":"mKHh.dart","source":"renamed.source","timestamp":1654528833152}]}