{"version":1,"resource":"file:///Users/pm/Project/zanalys-app-flutter/packages/common/lib/src/widgets/app_bars.dart","entries":[{"id":"TeQ0.dart","timestamp":1655180400938},{"id":"ijnH.dart","timestamp":1655180430326},{"id":"rpcv.dart","timestamp":1655180471334},{"id":"zfFD.dart","timestamp":1655180485492},{"id":"jR9Q.dart","timestamp":1655180544818},{"id":"wLS8.dart","timestamp":1655180561394},{"id":"XtVy.dart","timestamp":1655180572681},{"id":"UH2m.dart","timestamp":1655180646283},{"id":"Rhd4.dart","timestamp":1655180660407},{"id":"8GWv.dart","timestamp":1655180687194},{"id":"tfoV.dart","timestamp":1655180885593},{"id":"2lON.dart","timestamp":1655180906976},{"id":"2gB0.dart","timestamp":1655180943417},{"id":"zpxk.dart","timestamp":1655181043502},{"id":"GHW8.dart","timestamp":1655181135231},{"id":"LN0Y.dart","timestamp":1655181196936},{"id":"4TAc.dart","timestamp":1655181279812},{"id":"rCnc.dart","timestamp":1655181291854},{"id":"tIq0.dart","timestamp":1655181317755},{"id":"oM7V.dart","timestamp":1655181354419},{"id":"Uykv.dart","timestamp":1655181414504},{"id":"mIuc.dart","timestamp":1655181439331},{"id":"fgHL.dart","timestamp":1655181453067},{"id":"wRVQ.dart","timestamp":1655181483650},{"id":"evvj.dart","source":"undoRedo.source","timestamp":1655181489625},{"id":"dAmI.dart","timestamp":1655181503026},{"id":"0crB.dart","source":"undoRedo.source","timestamp":1655181530997},{"id":"OtjQ.dart","timestamp":1655181556012},{"id":"8PmI.dart","timestamp":1655181578711},{"id":"buiD.dart","timestamp":1655181607976},{"id":"uAwl.dart","timestamp":1655181645252},{"id":"HMMc.dart","timestamp":1655181676319},{"id":"UGmo.dart","timestamp":1655181819193},{"id":"1AvP.dart","timestamp":1655182266695},{"id":"BdWZ.dart","timestamp":1655183196571},{"id":"33sE.dart","timestamp":1655183440488},{"id":"99bE.dart","timestamp":1655183467258},{"id":"xFp8.dart","timestamp":1655183488533},{"id":"NsZi.dart","timestamp":1655183579804},{"id":"MVo7.dart","source":"undoRedo.source","timestamp":1655183585019},{"id":"Ejnm.dart","timestamp":1655216734454},{"id":"fhLy.dart","source":"undoRedo.source","timestamp":1655216821250},{"id":"IB5b.dart","timestamp":1655217505305},{"id":"qS5y.dart","timestamp":1655217522734},{"id":"8M63.dart","timestamp":1655217562768},{"id":"LK7i.dart","timestamp":1655217589120},{"id":"0srC.dart","timestamp":1655217642840},{"id":"IbDG.dart","timestamp":1655217667180},{"id":"gr4m.dart","timestamp":1655366244147},{"id":"5hhC.dart","timestamp":1655458749670}]}