{"version":1,"resource":"file:///Users/pm/Project/zanalys/zanalys-app-flutter/packages/zanalys_api/lib/zanalys_api.dart","entries":[{"id":"M9lc.dart","timestamp":1655820127716},{"id":"WMJg.dart","timestamp":1655822211271},{"id":"q6p6.dart","timestamp":1655822260105},{"id":"kQqy.dart","timestamp":1655905324201},{"id":"isVz.dart","timestamp":1655971397077},{"id":"LhXD.dart","timestamp":1655971416222},{"id":"YKSv.dart","timestamp":1655973538365},{"id":"SE35.dart","timestamp":1655975736253},{"id":"f01d.dart","source":"Workspace Edit","timestamp":1657879782603},{"id":"zkj0.dart","timestamp":1657879910008},{"id":"cxRJ.dart","timestamp":1658042596055},{"id":"QBHi.dart","timestamp":1658231349826},{"id":"7W4d.dart","timestamp":1658231440152},{"id":"aRbx.dart","timestamp":1658653594663},{"id":"c6LG.dart","timestamp":1658655276682},{"id":"dHSk.dart","timestamp":1658655337598},{"id":"HClT.dart","timestamp":1658655373458}]}